cgts_client/__init__.py
cgts_client-0.0.3.dist-info/LICENSE
cgts_client-0.0.3.dist-info/METADATA
cgts_client-0.0.3.dist-info/WHEEL
cgts_client-0.0.3.dist-info/entry_points.txt
cgts_client-0.0.3.dist-info/top_level.txt
cgts_client-0.0.3.dist-info/RECORD
